{
  "categories": {
    "person": {
      "label": "人物",
      "color": "#66ccff"
    }
  },
  "data": {
    "nodes": [
      {
        "id": "3728",
        "label": "大崎娜娜",
        "info": "アニメでの声優：朴璐美/アニメでの歌唱役：土屋アンナ/PS2ゲームでの声優：皆川純子/映画1・2：中島美嘉",
        "image": "https://lain.bgm.tv/pic/crt/m/e9/62/3728_crt_cr27b.jpg?r=1405365065",
        "link": "https://bgm.tv/character/3728",
        "categorie": "person"
      },
      {
        "id": "4559",
        "label": "本城莲",
        "info": "元ブラストのベース担当で、現在はトラネスのギターと作曲を担当。ナナの恋人。生後間もなく、港の倉庫街で捨てられているところを発見され、ヤスと同じ施設で育った。バンドを始めた当初はヤスや他のメンバーと共にバンド「ブルート」を組んでいた。しかしメンバーに対する不満などからブルートを解散し、ヤス、中学の後輩であったノブ、その友人であったナナと共にブラストを結成。ブラストではノブにギターを担当させ、自身はベースを担当した。その後、トラネスのメジャーデビュー直前に抜けた前のギターの代わりにとタクミに引き抜かれ、トラネスメンバーになる。これによってトラネスは歴代最強メンバーと称されることとなった。",
        "image": "https://lain.bgm.tv/pic/crt/m/a5/b9/4559_crt_anidb.jpg",
        "link": "https://bgm.tv/character/4559",
        "categorie": "person"
      },
      {
        "id": "16926",
        "label": "小松奈奈",
        "info": "16巻で21歳を迎えた。コミック1巻第1話では18歳（高校3年生）、2巻から16巻まで20歳。",
        "image": "https://lain.bgm.tv/pic/crt/m/07/fb/16926_crt_r024r.jpg",
        "link": "https://bgm.tv/character/16926",
        "categorie": "person"
      },
      {
        "id": "16927",
        "label": "一之濑巧",
        "info": "トラネスのリーダーであり、ベース担当及びプロデューサーでもある。黒い長髪がトレードマーク。レイラや蓮ほどの人気は無く、名前を覚えられていないのか、一般人からは「トラネスのロンゲの人」と言われる事もしばしば。それ故、事務所からは髪型を変える事を禁じられている。普段は仕事の事ばかり考えているタイプの人間。頭の回転が非常に早く、とっさの判断による対応で周囲の人間のピンチを救うこともある。",
        "image": "https://lain.bgm.tv/pic/crt/m/e7/cc/16927_crt_6D34L.jpg",
        "link": "https://bgm.tv/character/16927",
        "categorie": "person"
      },
      {
        "id": "4557",
        "label": "寺岛伸夫",
        "info": "初登場18歳。現時点で21歳。",
        "image": "https://lain.bgm.tv/pic/crt/m/35/96/4557_crt_anidb.jpg",
        "link": "https://bgm.tv/character/4557",
        "categorie": "person"
      },
      {
        "id": "4558",
        "label": "高木泰士",
        "info": "初登場21歳。現時点で23～24歳。4月生まれらしい。",
        "image": "https://lain.bgm.tv/pic/crt/m/95/25/4558_crt_anidb.jpg",
        "link": "https://bgm.tv/character/4558",
        "categorie": "person"
      },
      {
        "id": "4576",
        "label": "藤枝直树",
        "info": "中学時代にタクミと知り合い、地味な青春を抜け出したいという理由からバンド活動を始め、後に正式なトラネスのドラマーとなる。タクミと同じくバンドメンバーの中では人気があまりないせいか、「トラネスの金髪の人」と呼ばれる。グラムロックが好きなど、かなりの派手好き。",
        "image": "https://lain.bgm.tv/pic/crt/m/f8/93/4576_crt_anidb.jpg",
        "link": "https://bgm.tv/character/4576",
        "categorie": "person"
      },
      {
        "id": "16928",
        "label": "冈崎真一",
        "info": "3巻初登場から12巻まで15歳（当初は兄のプロフィールを利用し18歳と偽っていた）。現時点で16歳。",
        "image": "https://lain.bgm.tv/pic/crt/m/01/d4/16928_crt_5g9Z9.jpg",
        "link": "https://bgm.tv/character/16928",
        "categorie": "person"
      },
      {
        "id": "16929",
        "label": "芹泽蕾拉",
        "info": "アニメでの声優：平野綾/アニメでの歌唱役：OLIVIA",
        "image": "https://lain.bgm.tv/pic/crt/m/3b/f2/16929_crt_LG6oP.jpg",
        "link": "https://bgm.tv/character/16929",
        "categorie": "person"
      },
      {
        "id": "27572",
        "label": "上原美里",
        "info": "BLACK STONESの地元時代からの熱狂的なファン。ナナ自身でさえ知らないナナの生い立ちに関してかなり詳しい少女。後にヤスの尋問により「上原美里」は偽名と判明したのち、高校を中退してブラストの事務所に就職した際に本名を明かしたが、かつてのなじみから、現在でもメンバーから美里と呼ばれている。金髪の縦ロールヘアだったが、就職活動のため黒のボブに変更。その後再び金髪になった。",
        "image": "https://lain.bgm.tv/pic/crt/m/a1/94/27572_crt_145YG.jpg",
        "link": "https://bgm.tv/character/27572",
        "categorie": "person"
      },
      {
        "id": "27574",
        "label": "诸星银平",
        "info": "バンド\"BLACK STONES\"のチーフマネージャー。登場時28歳。通称・銀ちゃん。オネエ言葉を喋る。痩身の多い『NANA』の登場人物の中では貴重な、がっちりしたイカツイ体格。ヤスが一番好き。美雨とヤスの交際を一番苦々しく思っていたりもする。またシンに対しても甘い。",
        "image": "https://lain.bgm.tv/pic/crt/m/0d/a0/27574_crt_2pp2n.jpg",
        "link": "https://bgm.tv/character/27574",
        "categorie": "person"
      },
      {
        "id": "27575",
        "label": "筱田美雨",
        "info": "通称「ミュー」。芸名は「美雨」のみ。27歳だが、仕事上では22歳ということにしている。四海コーポレーション所属の売れない女優。人生経験が豊富な割には恋愛に関して非常に晩熟で今のところ結婚願望は無い。ナナの婚約と前後してヤスと交際をはじめる。Vシネマ出演をきっかけに麻雀が強くなり、麻雀の腕はシンよりもさらに上。着付けの師範免許を持っている。",
        "image": "https://lain.bgm.tv/pic/crt/m/da/6a/27575_crt_383sk.jpg?r=1490397021",
        "link": "https://bgm.tv/character/27575",
        "categorie": "person"
      },
      {
        "id": "27576",
        "label": "香坂百合",
        "info": "本名は松本朝海（まつもと あさみ）。22歳。家出をした所を事務所に拾われ清純派アイドルとしてデビューするも売れず、やがて少しずつグラビアアイドルとして活躍し、のちに売れっ子AV女優として活躍。演技力はかなりのものである。ストーカー被害を避けるという名目で（本当は男に貢ぎ過ぎてお金がなくなってしまったため）四海コーポレーションの寮に住んでいる。それがきっかけでノブと親密になり、現在は交際中。特技は｢色仕掛け｣。少々勝気で現実的。ナナ同様女王様気質で、自己陶酔な面も。美雨の事を嫌っている節がある。雰囲気や巻き髪が何となく奈々に似ている。トラネスメンバーの中ではナオキが一番好き。",
        "image": "https://lain.bgm.tv/pic/crt/m/66/58/27576_crt_6IRZ0.jpg",
        "link": "https://bgm.tv/character/27576",
        "categorie": "person"
      },
      {
        "id": "27593",
        "label": "早乙女淳子",
        "info": "高校時代からの奈々の親友。美大生で、油絵が専門らしい。",
        "image": "https://lain.bgm.tv/pic/crt/m/38/37/27593_crt_ZNe38.jpg",
        "link": "https://bgm.tv/character/27593",
        "categorie": "person"
      },
      {
        "id": "27594",
        "label": "高倉京助",
        "info": "淳子の恋人。淳子と同じ美大に通う。専攻は油絵。好みのタイプは、背が高く色黒の女性（淳子はこの条件にピッタリ当てはまる）。淳子ともども非常に大人びているので、奈々から「熟年カップル」とよく言われる。もともとは章司の高校の同級生で、当時は「同時に何人もの女に手を出すろくでなし」だったらしい。特に3年生のときが一番のモテ期だったが、その時に本気で惚れていた同級生の姉に遊ばれた事があった。「女に優しく、男に厳しく」がモットー。奈々に対して、かなり甘い。上京してからは奈々の父親的存在。",
        "image": "https://lain.bgm.tv/pic/crt/m/f5/c2/27594_crt_2FwRp.jpg",
        "link": "https://bgm.tv/character/27594",
        "categorie": "person"
      },
      {
        "id": "27595",
        "label": "远藤章司",
        "info": "奈々の元彼。淳子とは幼馴染であり、一年浪人した後同じ美大に通う。地元の専門学校で奈々と出会い恋人になるが、奈々の上京後アルバイト先のファミリーレストランで幸子と出会う。ちょうどその頃は奈々のわがままぶりに疲れていたこともあり、二股をかけた末、幸子を選んだことで奈々に捨てられた。いわゆるヘタレで大胆さに欠けるが、真っ直ぐで嘘のつけない性格。奈々曰く「喋ると馬鹿っぽい」。「淳子の部屋」で、奈々に振られて以降の扱いのひどさを嘆いていた。",
        "image": "https://lain.bgm.tv/pic/crt/m/63/1d/27595_crt_yQIkT.jpg",
        "link": "https://bgm.tv/character/27595",
        "categorie": "person"
      },
      {
        "id": "27596",
        "label": "川村幸子",
        "info": "章司のバイトの後輩で、美大の同級生。現在の章司の恋人。背が小さく、章司の好みの女性。奈々と章司がすれ違い始めたころにバイト先の同僚になり、急接近する。章司に彼女がいると知っても諦めきれずに一緒にいようとしたことで章司の心を捉え、二股の末に彼女に成り代わった。",
        "image": "https://lain.bgm.tv/pic/crt/m/88/ed/27596_crt_akkkY.jpg",
        "link": "https://bgm.tv/character/27596",
        "categorie": "person"
      },
      {
        "id": "27597",
        "label": "佐藤公一",
        "info": "奈々らの行きつけのバー・ジャクソンホールのマスター。看板メニューのジャクソンバーガーは絶品。何故かいつもフルネームで呼ばれる。記憶力が良い。",
        "image": "https://lain.bgm.tv/pic/crt/m/e3/40/27597_crt_ENX8N.jpg",
        "link": "https://bgm.tv/character/27597",
        "categorie": "person"
      },
      {
        "id": "27598",
        "label": "水越诚一",
        "info": "奈々の東京での最初のバイト先「サブリナ」の店長。29歳。奈々を雇って1ヶ月ほどで廃業し、故郷に帰って幼馴染と結婚した。妻の名前は春江。淳子のことを（「ナナ」「ハチ」の続きという意味なのか）「キューちゃん」と呼ぶ。",
        "image": "https://lain.bgm.tv/pic/crt/m/5a/18/27598_crt_6660r.jpg",
        "link": "https://bgm.tv/character/27598",
        "categorie": "person"
      }
    ],
    "edges": []
  }
}