{
  "categories": {
    "person": {
      "label": "人物",
      "color": "#66ccff"
    }
  },
  "data": {
    "nodes": [
      {
        "id": "22952",
        "label": "岛田真梦",
        "info": "15歳の高校1年生。11月7日生まれの蠍座。血液型はO型。身長159cm、体重46kg、B75/W57/H83。出身地は東京都杉並区、趣味は歌、好きなものはひよこ、嫌いなものはうそ。",
        "image": "https://lain.bgm.tv/pic/crt/m/89/46/22952_crt_dmIJ0.jpg?r=1394815983",
        "link": "https://bgm.tv/character/22952",
        "categorie": "person"
      },
      {
        "id": "22956",
        "label": "林田蓝里",
        "info": "",
        "image": "https://lain.bgm.tv/pic/crt/m/a4/a3/22956_crt_pcpP6.jpg?r=1500915333",
        "link": "https://bgm.tv/character/22956",
        "categorie": "person"
      },
      {
        "id": "22957",
        "label": "片山实波",
        "info": "",
        "image": "https://lain.bgm.tv/pic/crt/m/08/77/22957_crt_w999x.jpg?r=1500915829",
        "link": "https://bgm.tv/character/22957",
        "categorie": "person"
      },
      {
        "id": "22958",
        "label": "七濑佳乃",
        "info": "",
        "image": "https://lain.bgm.tv/pic/crt/m/a3/86/22958_crt_EpQsI.jpg?r=1500916273",
        "link": "https://bgm.tv/character/22958",
        "categorie": "person"
      },
      {
        "id": "22959",
        "label": "久海菜菜美",
        "info": "",
        "image": "https://lain.bgm.tv/pic/crt/m/d6/28/22959_crt_o5NLw.jpg?r=1500916879",
        "link": "https://bgm.tv/character/22959",
        "categorie": "person"
      },
      {
        "id": "22960",
        "label": "菊间夏夜",
        "info": "",
        "image": "https://lain.bgm.tv/pic/crt/m/31/d6/22960_crt_YL111.jpg?r=1500917453",
        "link": "https://bgm.tv/character/22960",
        "categorie": "person"
      },
      {
        "id": "22961",
        "label": "冈本未夕",
        "info": "",
        "image": "https://lain.bgm.tv/pic/crt/m/b3/cc/22961_crt_7G6X7.jpg?r=1501341642",
        "link": "https://bgm.tv/character/22961",
        "categorie": "person"
      },
      {
        "id": "23026",
        "label": "大田邦良",
        "info": "住在仙台的偶像團體「I-1」的高級粉絲。很在意離開「I-1」的島田真夢，在公園看到有關Wake Up,Girls!演出的傳單上看到島田真夢的名字後十分驚訝。",
        "image": "https://lain.bgm.tv/pic/crt/m/b0/44/23026_crt_ayLTB.jpg?r=1390241993",
        "link": "https://bgm.tv/character/23026",
        "categorie": "person"
      },
      {
        "id": "23056",
        "label": "丹下顺子",
        "info": "事務所の社長。ヘビースモーカーで禁煙の場所でも平気で吸っている。東京・大阪と事務所を経営した後仙台に流れ着いたため全くの素人というわけではなく、敏腕プロデューサーの側面もあるためタレントも何人か所属し育成していたが、退社や廃業によって所属タレントが0の状態に陥った時にアイドルグループの構想を得る。部下の松田に罵詈雑言を浴びせるだけでなく、ムチャぶりの指示によりタレント探しを命じた[5]。WUGデビュー直前に運転資金を持ち逃げしてしまった（愛するダーリンが緊急事態のため）[6]。偶然WUGが営業に来ていた健康ランドで再会。須藤の悪行を裁く過程で社長業に復帰している。",
        "image": "https://lain.bgm.tv/pic/crt/m/40/0b/23056_crt_UNv6U.jpg?r=1501342209",
        "link": "https://bgm.tv/character/23056",
        "categorie": "person"
      },
      {
        "id": "37906",
        "label": "岩崎志保",
        "info": "双子座、高校2年、出身地は栃木県、趣味はDVD鑑賞、好きなものは晴れの日、嫌いなものは幽霊。",
        "image": "https://lain.bgm.tv/pic/crt/m/21/71/37906_crt_Q3arg.jpg",
        "link": "https://bgm.tv/character/37906",
        "categorie": "person"
      },
      {
        "id": "37907",
        "label": "近藤麻衣",
        "info": "射手座、出身地は福岡県、趣味は読書、好きなものは根性、嫌いなものは弱音。",
        "image": "https://lain.bgm.tv/pic/crt/m/5b/2f/37907_crt_G5thp.jpg",
        "link": "https://bgm.tv/character/37907",
        "categorie": "person"
      },
      {
        "id": "37908",
        "label": "吉川爱",
        "info": "高校1年、双子座、出身地は東京都、趣味はショッピング、好きなものは猫、嫌いなものはアボカド。",
        "image": "https://lain.bgm.tv/pic/crt/m/95/8f/37908_crt_wtRTQ.jpg",
        "link": "https://bgm.tv/character/37908",
        "categorie": "person"
      },
      {
        "id": "37909",
        "label": "相泽菜野花",
        "info": "大学2年、獅子座、出身地は熊本県、趣味は寝ること、好きなものは健康、嫌いなものは尖ったもの。",
        "image": "https://lain.bgm.tv/pic/crt/m/e5/db/37909_crt_YhMcx.jpg",
        "link": "https://bgm.tv/character/37909",
        "categorie": "person"
      },
      {
        "id": "37910",
        "label": "铃木萌歌",
        "info": "中学2年、獅子座、出身地は東京都、趣味と好きなものはアニメ・ゲーム、嫌いなものはトマト。",
        "image": "https://lain.bgm.tv/pic/crt/m/2a/40/37910_crt_KfsSK.jpg",
        "link": "https://bgm.tv/character/37910",
        "categorie": "person"
      },
      {
        "id": "49346",
        "label": "松田耕平",
        "info": "GREEN LEAVES ENTERTAINMENT事务所经理人，做事比较窝囊，但仍会尽力照顾WUG。在社长连夜潜逃后，曾顶任为社长，差点令接下风俗表演的WUG陷入困境而被顺子拯救。",
        "image": "https://lain.bgm.tv/pic/crt/m/b9/65/49346_crt_diJZ8.jpg?r=1501342847",
        "link": "https://bgm.tv/character/49346",
        "categorie": "person"
      },
      {
        "id": "28115",
        "label": "广播",
        "info": "各作品通用广播/播音员。",
        "image": "https://lain.bgm.tv/pic/crt/m/70/d8/28115_crt_vL10O.jpg",
        "link": "https://bgm.tv/character/28115",
        "categorie": "person"
      }
    ],
    "edges": []
  }
}