{
  "categories": {
    "person": {
      "label": "人物",
      "color": "#66ccff"
    }
  },
  "data": {
    "nodes": [
      {
        "id": "6614",
        "label": "地场卫",
        "info": "CV:古谷徹（テレビアニメ）、緒方恵美（劇場版R）※幼少期のみ、野島健児（Crystal） ",
        "image": "https://lain.bgm.tv/pic/crt/m/89/8d/6614_crt_wG7bf.jpg?r=1517680585",
        "link": "https://bgm.tv/character/6614",
        "categorie": "person"
      },
      {
        "id": "6577",
        "label": "月野兔",
        "info": "月野兔，是著名的日本动漫《美少女战士》中的主人翁，中文昵称阿兔或小兔。",
        "image": "https://lain.bgm.tv/pic/crt/m/51/22/6577_crt_2kuVO.jpg?r=1465480986",
        "link": "https://bgm.tv/character/6577",
        "categorie": "person"
      },
      {
        "id": "6581",
        "label": "水野亚美",
        "info": "IQ300的天才少女。9月10日出生，全国成绩第一的中学生，可变身成水星仙子Sailor Mercury。父亲是日本画家，母亲是医生，住在高级住宅。她梦想是成为一个出色的医生。",
        "image": "https://lain.bgm.tv/pic/crt/m/86/0f/6581_crt_NN64z.jpg?r=1465481343",
        "link": "https://bgm.tv/character/6581",
        "categorie": "person"
      },
      {
        "id": "6587",
        "label": "火野丽",
        "info": "居住在火川神社的巫女。4月17日出生，本身有很强的灵感，有灵力能驱赶恶灵，可变身成Sailor Mars。时常与小兔斗嘴，其实心里很关心她。",
        "image": "https://lain.bgm.tv/pic/crt/m/6a/fb/6587_crt_E51yy.jpg?r=1465481752",
        "link": "https://bgm.tv/character/6587",
        "categorie": "person"
      },
      {
        "id": "6592",
        "label": "木野真琴",
        "info": "沉醉在恋爱中的怪力少女。12月5日出生，力量十分强壮，可变身成Sailor Jupiter。和小兔是同一所学校但是穿的是转学之前的制服，原因是没有大尺寸的制服。非常害怕飞机，事缘因为她父母是在飞机上遇到空难而死。守护星是木星，兴趣是做家务、厨艺、园艺。对以前暗恋过的学长念念不忘，经常说男生“好像我以前喜欢的学长（师兄）”。",
        "image": "https://lain.bgm.tv/pic/crt/m/8a/1a/6592_crt_Q21q1.jpg?r=1465481530",
        "link": "https://bgm.tv/character/6592",
        "categorie": "person"
      },
      {
        "id": "6594",
        "label": "爱野美奈子",
        "info": "爱野美奈子，是著名的日本动漫《美少女战士》中的主要人物之一。五战士中最早觉醒的人。她有一只公猫叫阿尔特米斯，跟小兔的黑猫露娜是恋人，可变身成Sailor Venus。使用金星力量，漫画提及在苏醒成为Sailor Venus前，她一直都是以水手V（Sailor V）身份作战，目的是击败黑暗帝国的敌人和找寻同伴。与Sailor Moon一样，她拥有一只月亮形的镜子，是变身的法宝，梦想成为名歌手，守护星金星，经验比其他战士丰富，是四个守护神战士的首领。",
        "image": "https://lain.bgm.tv/pic/crt/m/72/45/6594_crt_E9D9C.jpg?r=1465481690",
        "link": "https://bgm.tv/character/6594",
        "categorie": "person"
      },
      {
        "id": "6699",
        "label": "露娜",
        "info": "会说话的雌性黑猫，额头上有一个弯月形状的记号，如果被贴住会不能说话而且其他的能力也会大大降低。登场时以寻找战士和月亮公主为目标。是月野兔的伙伴。",
        "image": "https://lain.bgm.tv/pic/crt/m/59/58/6699_crt_anidb.jpg",
        "link": "https://bgm.tv/character/6699",
        "categorie": "person"
      },
      {
        "id": "6684",
        "label": "小小兔",
        "info": "罗马拼音：Chibiusa",
        "image": "https://lain.bgm.tv/pic/crt/m/d8/1b/6684_crt_w0m59.jpg?r=1510268042",
        "link": "https://bgm.tv/character/6684",
        "categorie": "person"
      },
      {
        "id": "6721",
        "label": "冥王刹那",
        "info": "外部太阳系三战士之一，年龄是十位水手战士中最大的一个，很有大姐姐的风范，知识渊博，与小小兔是非常要好的朋友，非常照顾土萌萤。 变身后为Sailor Pluto 水兵冥王星，负责掌握著时间之轮。“刹”这个名字即是指“极短的时间”，与天王之“遥”、海王之“满”相呼应。",
        "image": "https://lain.bgm.tv/pic/crt/m/b7/8b/6721_crt_gw8GB.jpg?r=1510268053",
        "link": "https://bgm.tv/character/6721",
        "categorie": "person"
      },
      {
        "id": "6705",
        "label": "阿尔特米斯",
        "info": "雄性白猫，跟露娜一样会说人类的语言，是金星水手爱野美奈子的搭档。在月亮王国时，它与露娜是恋人，在30世纪时，和露娜诞下女儿戴安娜。",
        "image": "https://lain.bgm.tv/pic/crt/m/1e/8a/6705_crt_anidb.jpg",
        "link": "https://bgm.tv/character/6705",
        "categorie": "person"
      },
      {
        "id": "7055",
        "label": "プリンス・デマンド",
        "info": "",
        "image": "https://lain.bgm.tv/pic/crt/m/e1/43/7055_crt_anidb.jpg",
        "link": "https://bgm.tv/character/7055",
        "categorie": "person"
      },
      {
        "id": "7004",
        "label": "蒼のサフィール",
        "info": "",
        "image": "https://lain.bgm.tv/pic/crt/m/31/5b/7004_crt_anidb.jpg",
        "link": "https://bgm.tv/character/7004",
        "categorie": "person"
      },
      {
        "id": "6978",
        "label": "紅のルベウス",
        "info": "",
        "image": "https://lain.bgm.tv/pic/crt/m/cc/06/6978_crt_anidb.jpg",
        "link": "https://bgm.tv/character/6978",
        "categorie": "person"
      },
      {
        "id": "6998",
        "label": "翠のエスメロード",
        "info": "",
        "image": "https://lain.bgm.tv/pic/crt/m/3d/48/6998_crt_anidb.jpg",
        "link": "https://bgm.tv/character/6998",
        "categorie": "person"
      },
      {
        "id": "7113",
        "label": "ワイズマン",
        "info": "",
        "image": "https://lain.bgm.tv/pic/crt/m/35/01/7113_crt_anidb.jpg",
        "link": "https://bgm.tv/character/7113",
        "categorie": "person"
      },
      {
        "id": "6919",
        "label": "月野育子",
        "info": "",
        "image": "https://lain.bgm.tv/pic/crt/m/b6/70/6919_crt_anidb.jpg",
        "link": "https://bgm.tv/character/6919",
        "categorie": "person"
      },
      {
        "id": "6921",
        "label": "月野谦之",
        "info": "",
        "image": "https://lain.bgm.tv/pic/crt/m/39/e9/6921_crt_anidb.jpg",
        "link": "https://bgm.tv/character/6921",
        "categorie": "person"
      },
      {
        "id": "6920",
        "label": "月野进悟",
        "info": "うさぎの弟で小学生だが、かなり生意気でませた性格。やたら偉そうな態度で姉のことをバカにしている。セーラームーンに関しては自身の姉とも知らず大ファンを公言しているが、「セーラームーンがバカうさぎなんて、ぜってぇありえねぇ」と斬り捨てている。",
        "image": "https://lain.bgm.tv/pic/crt/m/cf/85/6920_crt_EIx7i.jpg?r=1465482256",
        "link": "https://bgm.tv/character/6920",
        "categorie": "person"
      },
      {
        "id": "7407",
        "label": "大阪奈留",
        "info": "うさぎの親友で同級生。実家は宝飾店オサピーを営む。店名の由来は著者の編集担当の小佐野の愛称「OさP」（後にこの愛称はオサブーとなり、コミックスの後書きにたびたび登場する）。普段の言動からは分かりにくいが、うさぎによると（お金持ちの）お嬢様である。",
        "image": "https://lain.bgm.tv/pic/crt/m/8b/63/7407_crt_v9HeU.jpg?r=1465482897",
        "link": "https://bgm.tv/character/7407",
        "categorie": "person"
      },
      {
        "id": "7450",
        "label": "古幡元基",
        "info": "",
        "image": "https://lain.bgm.tv/pic/crt/m/23/4e/7450_crt_anidb.jpg",
        "link": "https://bgm.tv/character/7450",
        "categorie": "person"
      },
      {
        "id": "7408",
        "label": "海野ぐりお",
        "info": "",
        "image": "https://lain.bgm.tv/pic/crt/m/00/ee/7408_crt_lgRg5.jpg",
        "link": "https://bgm.tv/character/7408",
        "categorie": "person"
      },
      {
        "id": "6858",
        "label": "クィーン・セレニティ",
        "info": "",
        "image": "https://lain.bgm.tv/pic/crt/m/c5/54/6858_crt_anidb.jpg",
        "link": "https://bgm.tv/character/6858",
        "categorie": "person"
      },
      {
        "id": "6857",
        "label": "美达利亚女王",
        "info": "黑暗帝国的主脑，操纵整个黑暗帝国的邪魔根源。",
        "image": "https://lain.bgm.tv/pic/crt/m/83/34/6857_crt_EEMx9.jpg",
        "link": "https://bgm.tv/character/6857",
        "categorie": "person"
      },
      {
        "id": "6977",
        "label": "ペッツ",
        "info": "",
        "image": "https://lain.bgm.tv/pic/crt/m/31/2f/6977_crt_anidb.jpg",
        "link": "https://bgm.tv/character/6977",
        "categorie": "person"
      },
      {
        "id": "6976",
        "label": "カラベラス",
        "info": "",
        "image": "https://lain.bgm.tv/pic/crt/m/64/a4/6976_crt_anidb.jpg",
        "link": "https://bgm.tv/character/6976",
        "categorie": "person"
      },
      {
        "id": "6974",
        "label": "ベルチェ",
        "info": "",
        "image": "https://lain.bgm.tv/pic/crt/m/b1/1c/6974_crt_anidb.jpg",
        "link": "https://bgm.tv/character/6974",
        "categorie": "person"
      },
      {
        "id": "6973",
        "label": "コーアン",
        "info": "",
        "image": "https://lain.bgm.tv/pic/crt/m/ab/a6/6973_crt_2tkET.jpg",
        "link": "https://bgm.tv/character/6973",
        "categorie": "person"
      },
      {
        "id": "58888",
        "label": "浅沼一等",
        "info": "衛の後輩。原作と『Crystal』版では元麻布中学の1年生。またフルーツパーラー「クラウン」の常連で、同じく常連のまことと親しい。",
        "image": "https://lain.bgm.tv/pic/crt/m/cd/f4/58888_crt_hhoyF.jpg",
        "link": "https://bgm.tv/character/58888",
        "categorie": "person"
      },
      {
        "id": "58889",
        "label": "更科琴乃",
        "info": "ちびうさの同級生である九助の姉。T・A女学院超常現象研究部の部長。T・A女学院の学園祭の際にレイと親しくなり、レイがブラック・ムーン一族に連れ去られた時、レイのことをずっと心配していた。",
        "image": "https://lain.bgm.tv/pic/crt/m/0e/dd/58889_crt_0GBUJ.jpg",
        "link": "https://bgm.tv/character/58889",
        "categorie": "person"
      },
      {
        "id": "8083",
        "label": "桃原桃子",
        "info": "ちびうさの同級生で友達。両親が中華料理屋を経営している。ちびうさからは「ももちゃん」と呼ばれている。",
        "image": "https://lain.bgm.tv/pic/crt/m/8b/7e/8083_crt_PBA71.jpg",
        "link": "https://bgm.tv/character/8083",
        "categorie": "person"
      },
      {
        "id": "6831",
        "label": "昆扎特",
        "info": "地球的安迪米欧王子前世的手下，四位地球战士之首，在Sailor V的单行本以及漫画页中，均有把他和Sailor Venus放在一起，可见他的地位与Sailor V相等。以Sailor Venus为主角的漫画Sailor V中，在怪盗A的篇章，曾出现提示两人为恋人的画面（亦是怪盗A转向黑暗势力的契机）。古舒达与其余三位地球战士转世至地球后，原本要寻找安迪米欧王子继续为其效力，但却被贝尔女王迷惑利用，成为黑暗帝国四大天王首领，并指使他们去对付美少女战士。在涅夫莱特、杰达特、佐伊塞特相继失败并化为石头后，在对付美少女战士的过程中唤起了前世的记忆，虽然想借机拯救同伴和安迪米欧王子，但却失败化身为石头，并在对付梅塔莉雅之时保护了安迪米欧王子。",
        "image": "https://lain.bgm.tv/pic/crt/m/4d/0b/6831_crt_anidb.jpg",
        "link": "https://bgm.tv/character/6831",
        "categorie": "person"
      },
      {
        "id": "6768",
        "label": "杰戴特",
        "info": "黑暗帝国四天王之黑暗帝国远东支部长，在对战Sailor Moon、Sailor Mercury及Sailor Mars时，被Sailor Moon的月冕击到，一不注意被飞机压成重伤，回去之后因作战失败被贝尔女王施以长眠刑罚（动画版第13话）。在新版动画Crystal版本中，他前世是Sailor Mars的恋人。",
        "image": "https://lain.bgm.tv/pic/crt/m/9a/84/6768_crt_anidb.jpg",
        "link": "https://bgm.tv/character/6768",
        "categorie": "person"
      },
      {
        "id": "6828",
        "label": "涅夫莱特",
        "info": "黑暗帝国四天王北美支部长。动画旧版化名“彼得/三条院正人”为假身份，企图迷惑月野兔的好友奈留，之后两人却相恋。因为赛西达想夺取他的黑水晶，派出手下令他重伤，之后为保护奈留而灰飞烟灭（动画版第24话）。在新版动画Crystal版本中，他前世是Sailor Jupiter的恋人。",
        "image": "https://lain.bgm.tv/pic/crt/m/11/34/6828_crt_anidb.jpg",
        "link": "https://bgm.tv/character/6828",
        "categorie": "person"
      },
      {
        "id": "6830",
        "label": "佐伊赛特",
        "info": "黑暗帝国四天王之黑暗帝国欧洲支部长，在动画版中，为黑暗帝国四大天王之一，看似是古舒达的恋人。因暗害地场卫，违反贝尔女王要求将地场卫生擒的命令，因此被贝尔女王处死。（动画版第35话）",
        "image": "https://lain.bgm.tv/pic/crt/m/5e/9f/6830_crt_anidb.jpg?r=1509399578",
        "link": "https://bgm.tv/character/6830",
        "categorie": "person"
      },
      {
        "id": "8081",
        "label": "キラル",
        "info": "",
        "image": "https://lain.bgm.tv/pic/crt/m/4a/fe/8081_crt_anidb.jpg",
        "link": "https://bgm.tv/character/8081",
        "categorie": "person"
      },
      {
        "id": "8082",
        "label": "アキラル",
        "info": "",
        "image": "https://lain.bgm.tv/pic/crt/m/b9/e4/8082_crt_anidb.jpg",
        "link": "https://bgm.tv/character/8082",
        "categorie": "person"
      },
      {
        "id": "6680",
        "label": "戴安娜",
        "info": "雌性灰色小猫，露娜与阿尔特米斯的女儿，跟露娜和阿尔特米斯一样会说人类的语言。",
        "image": "https://lain.bgm.tv/pic/crt/m/cc/4e/6680_crt_U8yuM.jpg",
        "link": "https://bgm.tv/character/6680",
        "categorie": "person"
      }
    ],
    "edges": []
  }
}