{
  "categories": {
    "person": {
      "label": "人物",
      "color": "#66ccff"
    }
  },
  "data": {
    "nodes": [
      {
        "id": "15627",
        "label": "福莱尔·布兰",
        "info": "“斑衣笛手”小队的IFO少女驾驶员。",
        "image": "https://lain.bgm.tv/pic/crt/m/fd/6e/15627_crt_1LZMk.jpg",
        "link": "https://bgm.tv/character/15627",
        "categorie": "person"
      },
      {
        "id": "15628",
        "label": "爱莲娜·毕普鲁斯",
        "info": "“斑衣笛手”小队的IFO少女驾驶员。",
        "image": "https://lain.bgm.tv/pic/crt/m/82/20/15628_crt_zI7kh.jpg",
        "link": "https://bgm.tv/character/15628",
        "categorie": "person"
      },
      {
        "id": "15630",
        "label": "瞪羚",
        "info": "",
        "image": "https://lain.bgm.tv/pic/crt/m/28/89/15630_crt_OQDi0.jpg?r=1401297995",
        "link": "https://bgm.tv/character/15630",
        "categorie": "person"
      },
      {
        "id": "15625",
        "label": "深井·青",
        "info": "本作的男主角。13岁。于冲绳的离岛——磐户岛与老医师兼家人敏雄一同生活。父亲目前失踪，母亲貌似数年前也被绑架。",
        "image": "https://lain.bgm.tv/pic/crt/m/ee/f2/15625_crt_OmIoI.jpg",
        "link": "https://bgm.tv/character/15625",
        "categorie": "person"
      },
      {
        "id": "16443",
        "label": "布朗",
        "info": "",
        "image": "https://lain.bgm.tv/pic/crt/m/28/cc/16443_crt_pquZd.jpg",
        "link": "https://bgm.tv/character/16443",
        "categorie": "person"
      },
      {
        "id": "16444",
        "label": "イビチャ・タノヴィッチ",
        "info": "",
        "image": "https://lain.bgm.tv/pic/crt/m/84/78/16444_crt_3W637.jpg",
        "link": "https://bgm.tv/character/16444",
        "categorie": "person"
      },
      {
        "id": "16448",
        "label": "汉娜",
        "info": "",
        "image": "https://lain.bgm.tv/pic/crt/m/0b/34/16448_crt_8H8eE.jpg",
        "link": "https://bgm.tv/character/16448",
        "categorie": "person"
      },
      {
        "id": "16450",
        "label": "ナカムラ",
        "info": "",
        "image": "https://lain.bgm.tv/pic/crt/m/f1/2c/16450_crt_RiIBm.jpg",
        "link": "https://bgm.tv/character/16450",
        "categorie": "person"
      },
      {
        "id": "16451",
        "label": "エンドウ",
        "info": "",
        "image": "https://lain.bgm.tv/pic/crt/m/b1/d2/16451_crt_7119i.jpg",
        "link": "https://bgm.tv/character/16451",
        "categorie": "person"
      },
      {
        "id": "16452",
        "label": "布鲁诺",
        "info": "",
        "image": "https://lain.bgm.tv/pic/crt/m/7c/3b/16452_crt_55gol.jpg",
        "link": "https://bgm.tv/character/16452",
        "categorie": "person"
      },
      {
        "id": "16453",
        "label": "カネシロ・カズユキ",
        "info": "",
        "image": "https://lain.bgm.tv/pic/crt/m/eb/53/16453_crt_wJov5.jpg",
        "link": "https://bgm.tv/character/16453",
        "categorie": "person"
      },
      {
        "id": "16454",
        "label": "ニイガキ・テルヒコ",
        "info": "",
        "image": "https://lain.bgm.tv/pic/crt/m/2c/f9/16454_crt_j6SrC.jpg",
        "link": "https://bgm.tv/character/16454",
        "categorie": "person"
      }
    ],
    "edges": []
  }
}