{
  "categories": {
    "person": {
      "label": "人物",
      "color": "#66ccff"
    }
  },
  "data": {
    "nodes": [
      {
        "id": "22741",
        "label": "渡濑青叶",
        "info": "诚应高中1年生。",
        "image": "https://lain.bgm.tv/pic/crt/m/1d/36/22741_crt_h5XfZ.jpg?r=1388404100",
        "link": "https://bgm.tv/character/22741",
        "categorie": "person"
      },
      {
        "id": "22744",
        "label": "弓原雛",
        "info": "16歳で誠應高校に通う1年生。",
        "image": "https://lain.bgm.tv/pic/crt/m/67/7f/22744_crt_7n7k7.jpg?r=1583694470",
        "link": "https://bgm.tv/character/22744",
        "categorie": "person"
      },
      {
        "id": "22745",
        "label": "隼鹰·迪奥·温伯格",
        "info": "自由条約連合軍少尉。",
        "image": "https://lain.bgm.tv/pic/crt/m/6f/fb/22745_crt_0Je3S.jpg?r=1395073777",
        "link": "https://bgm.tv/character/22745",
        "categorie": "person"
      },
      {
        "id": "22746",
        "label": "仓光源吾",
        "info": "38歳で自由条約連合軍に所属している。",
        "image": "https://lain.bgm.tv/pic/crt/m/e5/e7/22746_crt_l9h16.jpg?r=1388403912",
        "link": "https://bgm.tv/character/22746",
        "categorie": "person"
      },
      {
        "id": "22747",
        "label": "丽妮·克莱茵贝克",
        "info": "自由条約連合軍に所属している。",
        "image": "https://lain.bgm.tv/pic/crt/m/4d/c0/22747_crt_gwHZt.jpg",
        "link": "https://bgm.tv/character/22747",
        "categorie": "person"
      },
      {
        "id": "22748",
        "label": "李·康拉德",
        "info": "自由条約連合軍に所属している。",
        "image": "https://lain.bgm.tv/pic/crt/m/7e/6a/22748_crt_8U0I8.jpg?r=1388404287",
        "link": "https://bgm.tv/character/22748",
        "categorie": "person"
      },
      {
        "id": "22749",
        "label": "亚尔·都兰",
        "info": "自由条約連合軍に所属している。",
        "image": "https://lain.bgm.tv/pic/crt/m/be/ad/22749_crt_0B9b7.jpg",
        "link": "https://bgm.tv/character/22749",
        "categorie": "person"
      },
      {
        "id": "22750",
        "label": "艾尔薇拉·希尔",
        "info": "特務士官。",
        "image": "https://lain.bgm.tv/pic/crt/m/98/aa/22750_crt_99Dya.jpg?r=1388404926",
        "link": "https://bgm.tv/character/22750",
        "categorie": "person"
      },
      {
        "id": "22752",
        "label": "奈须真由佳",
        "info": "16歳。自由条約連合軍に所属しており特務士官補佐をしている。",
        "image": "https://lain.bgm.tv/pic/crt/m/49/15/22752_crt_73hMt.jpg",
        "link": "https://bgm.tv/character/22752",
        "categorie": "person"
      },
      {
        "id": "22753",
        "label": "アネッサ・ロセッティ",
        "info": "自由条約連合軍伍長。管制士をしており、新造艦シグナスのヴァリアンサーの管制を担当している。親友のまゆかとは真逆で活発。",
        "image": "https://lain.bgm.tv/pic/crt/m/27/ce/22753_crt_3sBci.jpg",
        "link": "https://bgm.tv/character/22753",
        "categorie": "person"
      },
      {
        "id": "22754",
        "label": "奇赛·弗兰波瓦",
        "info": "26歳で自由条約連合軍に所属している。",
        "image": "https://lain.bgm.tv/pic/crt/m/8a/b2/22754_crt_V8Sm8.jpg",
        "link": "https://bgm.tv/character/22754",
        "categorie": "person"
      },
      {
        "id": "22755",
        "label": "格鲁斯安·巴斯",
        "info": "26歳で自由条約連合軍に所属している。",
        "image": "https://lain.bgm.tv/pic/crt/m/ce/ef/22755_crt_MOMui.jpg",
        "link": "https://bgm.tv/character/22755",
        "categorie": "person"
      },
      {
        "id": "22756",
        "label": "スハルト",
        "info": "23歳で自由条約連合軍に所属している。",
        "image": "https://lain.bgm.tv/pic/crt/m/16/88/22756_crt_4KIE6.jpg",
        "link": "https://bgm.tv/character/22756",
        "categorie": "person"
      },
      {
        "id": "22757",
        "label": "荻坂三郎太",
        "info": "30歳で自由条約連合軍に所属している。",
        "image": "https://lain.bgm.tv/pic/crt/m/df/1f/22757_crt_aWqW7.jpg",
        "link": "https://bgm.tv/character/22757",
        "categorie": "person"
      },
      {
        "id": "22758",
        "label": "ドン・ナッハー",
        "info": "55歳で自由条約連合軍に所属している。",
        "image": "https://lain.bgm.tv/pic/crt/m/09/48/22758_crt_pcrxC.jpg",
        "link": "https://bgm.tv/character/22758",
        "categorie": "person"
      },
      {
        "id": "22759",
        "label": "阿尔弗利德·加兰特",
        "info": "大ゾギリア共和国国防軍に所属している。",
        "image": "https://lain.bgm.tv/pic/crt/m/33/dd/22759_crt_IYE4T.jpg",
        "link": "https://bgm.tv/character/22759",
        "categorie": "person"
      },
      {
        "id": "22760",
        "label": "比宗·杰拉菲尔",
        "info": "大ゾギリア共和国国防军中尉。",
        "image": "https://lain.bgm.tv/pic/crt/m/83/89/22760_crt_6wN2L.jpg",
        "link": "https://bgm.tv/character/22760",
        "categorie": "person"
      },
      {
        "id": "49766",
        "label": "弗洛姆·范塔雷",
        "info": "",
        "image": "https://lain.bgm.tv/pic/crt/m/da/9d/49766_crt_yJ2oc.jpg",
        "link": "https://bgm.tv/character/49766",
        "categorie": "person"
      },
      {
        "id": "49767",
        "label": "塔基姆·瓦西里",
        "info": "",
        "image": "https://lain.bgm.tv/pic/crt/m/df/15/49767_crt_Eva2a.jpg",
        "link": "https://bgm.tv/character/49767",
        "categorie": "person"
      },
      {
        "id": "49768",
        "label": "拉夏·哈克莱宁",
        "info": "",
        "image": "https://lain.bgm.tv/pic/crt/m/05/3f/49768_crt_0KQss.jpg",
        "link": "https://bgm.tv/character/49768",
        "categorie": "person"
      },
      {
        "id": "49769",
        "label": "玛格丽塔·奥基弗",
        "info": "",
        "image": "https://lain.bgm.tv/pic/crt/m/b0/cc/49769_crt_WdcXT.jpg",
        "link": "https://bgm.tv/character/49769",
        "categorie": "person"
      },
      {
        "id": "49770",
        "label": "ヴィルヘルム・ハーン",
        "info": "",
        "image": "https://lain.bgm.tv/pic/crt/m/88/14/49770_crt_7NMWl.jpg",
        "link": "https://bgm.tv/character/49770",
        "categorie": "person"
      },
      {
        "id": "49771",
        "label": "ヴィクトル・リャザン",
        "info": "",
        "image": "https://lain.bgm.tv/pic/crt/m/51/fc/49771_crt_xeIoe.jpg",
        "link": "https://bgm.tv/character/49771",
        "categorie": "person"
      },
      {
        "id": "49772",
        "label": "隼鹰·菲奥娜·温伯格",
        "info": "",
        "image": "https://lain.bgm.tv/pic/crt/m/87/95/49772_crt_30h04.jpg",
        "link": "https://bgm.tv/character/49772",
        "categorie": "person"
      },
      {
        "id": "49773",
        "label": "隼鹰·贞道·温伯格",
        "info": "",
        "image": "https://lain.bgm.tv/pic/crt/m/40/2f/49773_crt_St7jQ.jpg",
        "link": "https://bgm.tv/character/49773",
        "categorie": "person"
      }
    ],
    "edges": []
  }
}